inkling/__init__.py
inkling-0.0.1.dist-info/METADATA
inkling-0.0.1.dist-info/WHEEL
inkling-0.0.1.dist-info/RECORD
