Metadata-Version: 2.4
Name: inkling
Version: 0.0.1
Summary: Coming soon.
Project-URL: Homepage, https://github.com/katiyar/inkling
Author: Inkling Team
License: MIT
Classifier: Development Status :: 1 - Planning
Classifier: License :: OSI Approved :: MIT License
Classifier: Programming Language :: Python :: 3
Requires-Python: >=3.10
